{"cameraMode":{"drawMode":0,"name":"Shaded","section":"Shading Mode"},"sceneLighting":true,"audioPlay":false,"sceneViewState":{"m_AlwaysRefresh":false,"showFog":true,"showSkybox":true,"showFlares":true,"showImageEffects":true,"showParticleSystems":true,"showVisualEffectGraphs":true,"m_FxEnabled":true},"in2DMode":false,"pivot":{"x":2.489999771118164,"y":0.673003077507019,"z":7.409999847412109},"rotation":{"x":-0.03329142928123474,"y":0.9519301652908325,"z":-0.11188612878322602,"w":-0.28324180841445925},"size":2.8250420093536379,"orthographic":false}